moonshot/__init__.py
moonshot/_cache.py
moonshot/_version.py
moonshot/exceptions.py
moonshot/py.typed
moonshot/_tests/__init__.py
moonshot/_tests/test_allow_rebalance.py
moonshot/_tests/test_backtest.py
moonshot/_tests/test_benchmark.py
moonshot/_tests/test_cache.py
moonshot/_tests/test_commissions.py
moonshot/_tests/test_limit_position_sizes.py
moonshot/_tests/test_ml.py
moonshot/_tests/test_orders.py
moonshot/_tests/test_positions_closed_daily.py
moonshot/_tests/test_prices.py
moonshot/_tests/test_save_custom_dataframe.py
moonshot/_tests/test_slippage.py
moonshot/_tests/test_trade.py
moonshot/_tests/test_trade_date_validation.py
moonshot/_tests/test_weight_allocations.py
moonshot/_tests/utils.py
moonshot/_tests/commission/__init__.py
moonshot/_tests/commission/test_commissions.py
moonshot/_tests/fixtures/__init__.py
moonshot/_tests/fixtures/test_model.keras.h5
moonshot/_tests/slippage/__init__.py
moonshot/_tests/slippage/test_slippage.py
moonshot/commission/__init__.py
moonshot/commission/base.py
moonshot/commission/fut.py
moonshot/commission/fx.py
moonshot/commission/stk.py
moonshot/mixins/__init__.py
moonshot/mixins/weight.py
moonshot/slippage/__init__.py
moonshot/slippage/base.py
moonshot/slippage/borrowfee.py
moonshot/slippage/fixed.py
moonshot/strategies/__init__.py
moonshot/strategies/base.py
moonshot/strategies/ml.py
quantrocket_moonshot-2.11.0.0.dist-info/LICENSE.txt
quantrocket_moonshot-2.11.0.0.dist-info/METADATA
quantrocket_moonshot-2.11.0.0.dist-info/WHEEL
quantrocket_moonshot-2.11.0.0.dist-info/top_level.txt
quantrocket_moonshot-2.11.0.0.dist-info/RECORD
