Metadata-Version: 2.1
Name: quantrocket-moonshot
Version: 2.11.0.0
Summary: Moonshot
Home-page: https://www.quantrocket.com
Author: QuantRocket LLC
Author-email: support@quantrocket.com
License: Apache-2.0
License-File: LICENSE.txt
Requires-Dist: quantrocket-client
Requires-Dist: pandas
Requires-Dist: filelock
